promean4py/__init__.py
ProcessMeaningPatternsPython-0.11.dist-info/LICENSE
ProcessMeaningPatternsPython-0.11.dist-info/METADATA
ProcessMeaningPatternsPython-0.11.dist-info/WHEEL
ProcessMeaningPatternsPython-0.11.dist-info/top_level.txt
ProcessMeaningPatternsPython-0.11.dist-info/RECORD
