Metadata-Version: 2.1
Name: ProcessMeaningPatternsPython
Version: 0.11
Summary: An app to map event logs into ontology-based process knowledge and analyze the data through a library of knowledge patterns
Home-page: https://github.com/riley-momo/ProcessMeaningPatternsPython
Author: Riley Moher
Author-email: riley.moher@mail.utoronto.ca
License: MIT
Classifier: Development Status :: 2 - Pre-Alpha
Classifier: Intended Audience :: Developers
Classifier: License :: OSI Approved :: MIT License
Classifier: Programming Language :: Python :: 3.9
Classifier: Natural Language :: English
Requires-Python: >=3.9
License-File: LICENSE
Requires-Dist: numpy
Requires-Dist: pandas
Requires-Dist: pm4py
Requires-Dist: kglab
Requires-Dist: yatter
Requires-Dist: ruamel.yaml
Provides-Extra: dev
Requires-Dist: twine>=4.0.2; extra == "dev"
